MANIFEST.in
README.md
setup.py
easy_pack/README.md
easy_pack/__init__.py
easy_pack/build.py
easy_pack/core.py
easy_pack/license.txt
easy_pack/scaffold.py
easy_pack/setup.cfg
easy_pack.egg-info/PKG-INFO
easy_pack.egg-info/SOURCES.txt
easy_pack.egg-info/dependency_links.txt
easy_pack.egg-info/not-zip-safe
easy_pack.egg-info/requires.txt
easy_pack.egg-info/top_level.txt
easy_pack/__pycache__/__init__.cpython-312.pyc
easy_pack/__pycache__/build.cpython-312.pyc
easy_pack/__pycache__/core.cpython-312.pyc
easy_pack/files/README.md
easy_pack/files/init.py
easy_pack/files/license.txt
easy_pack/files/license_MIT.txt
easy_pack/files/resources.py
easy_pack/files/__pycache__/resources.cpython-312.pyc