Metadata-Version: 2.1
Name: easy-pack
Version: 1.0.137
Summary: easy packing!
Home-page: https://github.com/germanespinosa/easy-pack
Author: german espinosa
Author-email: germanespinosa@gmail.com
License: MIT
Requires-Dist: twine
